face_sort/__init__.py
face_sort/cosinus_distance.py
face_sort/euclidean_distance.py
face_sort/extract_faces.py
face_sort/main.py
face_sort/sorted_cosinus_distance.py
face_sort/sorted_euclidean_distance.py
face_sort-0.2.0.dist-info/LICENSE
face_sort-0.2.0.dist-info/METADATA
face_sort-0.2.0.dist-info/WHEEL
face_sort-0.2.0.dist-info/entry_points.txt
face_sort-0.2.0.dist-info/top_level.txt
face_sort-0.2.0.dist-info/RECORD
