Metadata-Version: 2.2
Name: face_sort
Version: 0.2.0
Summary: Un outil de tri d'images par reconnaissance faciale.
Home-page: https://github.com/fkeunang/face_sort
Author: Farida Keunang Tchatchou
Classifier: Programming Language :: Python :: 3
Classifier: License :: OSI Approved :: MIT License
Requires-Python: >=3.8
License-File: LICENSE
Requires-Dist: certifi==2025.1.31
Requires-Dist: charset-normalizer==3.4.1
Requires-Dist: click==8.1.8
Requires-Dist: colorama==0.4.6
Requires-Dist: dlib==19.24.6
Requires-Dist: docutils==0.21.2
Requires-Dist: face-recognition==1.3.0
Requires-Dist: face_recognition_models==0.3.0
Requires-Dist: id==1.5.0
Requires-Dist: idna==3.10
Requires-Dist: jaraco.classes==3.4.0
Requires-Dist: jaraco.context==6.0.1
Requires-Dist: jaraco.functools==4.1.0
Requires-Dist: keyring==25.6.0
Requires-Dist: markdown-it-py==3.0.0
Requires-Dist: mdurl==0.1.2
Requires-Dist: more-itertools==10.6.0
Requires-Dist: nh3==0.2.21
Requires-Dist: numpy==2.2.3
Requires-Dist: opencv-python==4.11.0.86
Requires-Dist: packaging==24.2
Requires-Dist: pillow==11.1.0
Requires-Dist: Pygments==2.19.1
Requires-Dist: pywin32-ctypes==0.2.3
Requires-Dist: readme_renderer==44.0
Requires-Dist: requests==2.32.3
Requires-Dist: requests-toolbelt==1.0.0
Requires-Dist: rfc3986==2.0.0
Requires-Dist: rich==13.9.4
Requires-Dist: scipy==1.15.2
Requires-Dist: setuptools==76.0.0
Requires-Dist: twine==6.1.0
Requires-Dist: urllib3==2.3.0
Requires-Dist: wheel==0.45.1
Dynamic: author
Dynamic: classifier
Dynamic: description
Dynamic: description-content-type
Dynamic: home-page
Dynamic: requires-dist
Dynamic: requires-python
Dynamic: summary
